neterr/__init__.py
neterr-1.1.1.dist-info/LICENSE
neterr-1.1.1.dist-info/METADATA
neterr-1.1.1.dist-info/WHEEL
neterr-1.1.1.dist-info/top_level.txt
neterr-1.1.1.dist-info/RECORD
