Metadata-Version: 2.1
Name: neterr
Version: 1.1.1
Summary: Useful groupings of exceptions for working with network requests.
Home-page: https://github.com/polishmatt/neterr
Author: Matt Wisniewski
Author-email: hello@mattw.life
License: Apache License 2.0
Keywords: network,api,http,request
Platform: UNKNOWN
Classifier: Development Status :: 5 - Production/Stable
Classifier: Intended Audience :: Developers
Classifier: Environment :: Web Environment
Classifier: License :: OSI Approved :: Apache Software License
Classifier: Programming Language :: Python
Classifier: Programming Language :: Python :: 3 :: Only
Classifier: Programming Language :: Python :: 3.6
Classifier: Programming Language :: Python :: 3.7
Classifier: Topic :: Software Development :: Libraries :: Python Modules
Requires-Python: >=3.6.0
